{
  "project_info": {
    "project_number": "1071745330199",
    "project_id": "nodesonline-74eb2",
    "storage_bucket": "nodesonline-74eb2.appspot.com"
  },
  "client": [
    {
      "client_info": {
        "mobilesdk_app_id": "1:1071745330199:android:a8d01f8f1ebe32cf684052",
        "android_client_info": {
          "package_name": "com.example.nodesmainmenu.nodes"
        }
      },
      "oauth_client": [],
      "api_key": [
        {
          "current_key": "AIzaSyAsxdQMyOXf2b1q4aL7j2UGQFQfaVqL1Zo"
        }
      ],
      "services": {
        "appinvite_service": {
          "other_platform_oauth_client": []
        }
      }
    }
  ],
  "configuration_version": "1"
}